til/.til.toml.default
til/__init__.py
til/main.py
til/plugins/__init__.py
til/plugins/base.py
til/plugins/yaml.py
til/utils.py
til_cli-0.2.0.dist-info/entry_points.txt
til_cli-0.2.0.dist-info/WHEEL
til_cli-0.2.0.dist-info/METADATA
til_cli-0.2.0.dist-info/RECORD
