Metadata-Version: 2.1
Name: til-cli
Version: 0.2.0
Summary: Keep track of things you learn each day
Home-page: https://github.com/kamyar/til
License: MPL-2.0
Author: Kamyar Ghasemlou
Author-email: github@kamy.me
Requires-Python: >=3.6,<4.0
Classifier: License :: OSI Approved
Classifier: Programming Language :: Python :: 3
Classifier: Programming Language :: Python :: 3.6
Classifier: Programming Language :: Python :: 3.7
Classifier: Programming Language :: Python :: 3.8
Classifier: Programming Language :: Python :: 3.9
Requires-Dist: click (>=7.1.2,<8.0.0)
Requires-Dist: ruamel.yaml (>=0.17.4,<0.18.0)
Requires-Dist: toml (>=0.10.2,<0.11.0)
Project-URL: Repository, https://github.com/kamyar/til
